connect_spotify/__init__.py
connect_spotify/connection.py
connect_spotify-1.0.4.dist-info/METADATA
connect_spotify-1.0.4.dist-info/WHEEL
connect_spotify-1.0.4.dist-info/top_level.txt
connect_spotify-1.0.4.dist-info/RECORD
