Metadata-Version: 2.1
Name: connect-spotify
Version: 1.0.4
Summary: Connect to Spotify API with Streamlit
Home-page: UNKNOWN
License: MIT
Project-URL: Source, https://github.com/Satoshi-Sh/connect-spotify
Keywords: streamlit
Platform: UNKNOWN
Classifier: Development Status :: 5 - Production/Stable
Requires-Dist: requests
Requires-Dist: streamlit
